argdb/__init__.py
argdb/__main__.py
argdb/argdb.py
argdb/cli.py
argdb/config.py
argdb/gui.py
argdb/ui.py
argdb/version.py
tests/__init__.py
argdb-0.1.1.2.dist-info/LICENSE
argdb-0.1.1.2.dist-info/METADATA
argdb-0.1.1.2.dist-info/WHEEL
argdb-0.1.1.2.dist-info/top_level.txt
argdb-0.1.1.2.dist-info/RECORD
