Metadata-Version: 2.1
Name: argdb
Version: 0.1.1.2
Summary: ArgDB - A Datastore for arguments 
Home-page: https://github.com/Open-Argumentation/ArgDB
Author: Simon Wells
Author-email: mail@simonwells.org
License: Type license() to see the full license text
Platform: UNKNOWN
Requires-Dist: sadface
Requires-Dist: bottle
Requires-Dist: pywebview
